mo_future/__init__.py
mo_future/cache.py
mo_future-7.685.25166.dist-info/licenses/LICENSE
mo_future-7.685.25166.dist-info/METADATA
mo_future-7.685.25166.dist-info/WHEEL
mo_future-7.685.25166.dist-info/top_level.txt
mo_future-7.685.25166.dist-info/RECORD
